zavudev/__init__.py
zavudev/_base_client.py
zavudev/_client.py
zavudev/_compat.py
zavudev/_constants.py
zavudev/_exceptions.py
zavudev/_files.py
zavudev/_models.py
zavudev/_qs.py
zavudev/_resource.py
zavudev/_response.py
zavudev/_streaming.py
zavudev/_types.py
zavudev/_version.py
zavudev/pagination.py
zavudev/py.typed
zavudev/_utils/__init__.py
zavudev/_utils/_compat.py
zavudev/_utils/_datetime_parse.py
zavudev/_utils/_logs.py
zavudev/_utils/_proxy.py
zavudev/_utils/_reflection.py
zavudev/_utils/_resources_proxy.py
zavudev/_utils/_streams.py
zavudev/_utils/_sync.py
zavudev/_utils/_transform.py
zavudev/_utils/_typing.py
zavudev/_utils/_utils.py
zavudev/lib/.keep
zavudev/resources/__init__.py
zavudev/resources/addresses.py
zavudev/resources/contacts.py
zavudev/resources/introspect.py
zavudev/resources/messages.py
zavudev/resources/phone_numbers.py
zavudev/resources/regulatory_documents.py
zavudev/resources/templates.py
zavudev/resources/broadcasts/__init__.py
zavudev/resources/broadcasts/broadcasts.py
zavudev/resources/broadcasts/contacts.py
zavudev/resources/senders/__init__.py
zavudev/resources/senders/senders.py
zavudev/resources/senders/agent/__init__.py
zavudev/resources/senders/agent/agent.py
zavudev/resources/senders/agent/executions.py
zavudev/resources/senders/agent/flows.py
zavudev/resources/senders/agent/tools.py
zavudev/resources/senders/agent/knowledge_bases/__init__.py
zavudev/resources/senders/agent/knowledge_bases/documents.py
zavudev/resources/senders/agent/knowledge_bases/knowledge_bases.py
zavudev/types/__init__.py
zavudev/types/address.py
zavudev/types/address_create_params.py
zavudev/types/address_create_response.py
zavudev/types/address_list_params.py
zavudev/types/address_retrieve_response.py
zavudev/types/address_status.py
zavudev/types/available_phone_number.py
zavudev/types/broadcast.py
zavudev/types/broadcast_cancel_response.py
zavudev/types/broadcast_channel.py
zavudev/types/broadcast_contact.py
zavudev/types/broadcast_contact_status.py
zavudev-0.18.0.dist-info/METADATA
zavudev-0.18.0.dist-info/WHEEL
zavudev-0.18.0.dist-info/licenses/LICENSE
zavudev-0.18.0.dist-info/RECORD
